snapcastr/__init__.py
snapcastr/snapcastr.py
snapcastr/snapcastrd.py
snapcastr/static/snapcast.ico
snapcastr/static/style.css
snapcastr/templates/base.html
snapcastr/templates/clients.html
snapcastr/templates/groups.html
snapcastr/templates/streams.html
snapcastr/templates/zones.html
snapcastr-0.2.1.dist-info/entry_points.txt
snapcastr-0.2.1.dist-info/WHEEL
snapcastr-0.2.1.dist-info/METADATA
snapcastr-0.2.1.dist-info/RECORD
