Metadata-Version: 2.1
Name: snapcastr
Version: 0.2.1
Summary: webinterface to control a snapcast server
Home-page: https://github.com/xkonni/snapcastr
License: MIT
Author: xkonni
Author-email: konstantin.koslowski@gmail.com
Requires-Python: >=3.7,<4.0
Classifier: License :: OSI Approved :: MIT License
Classifier: Programming Language :: Python :: 3
Classifier: Programming Language :: Python :: 3.7
Classifier: Programming Language :: Python :: 3.8
Requires-Dist: Flask (>=1.1.2,<2.0.0)
Requires-Dist: flask-bootstrap (>=3.3.7,<4.0.0)
Requires-Dist: flask-nav (>=0.6,<0.7)
Requires-Dist: snapcast (>=2.1.0,<3.0.0)
Requires-Dist: wtforms (>=2.2.1,<3.0.0)
Requires-Dist: xdg (>=4.0.1,<5.0.0)
Project-URL: Repository, https://github.com/xkonni/snapcastr
